mglearn/__init__.py
mglearn/datasets.py
mglearn/plot_2d_separator.py
mglearn/plot_agglomerative.py
mglearn/plot_animal_tree.py
mglearn/plot_cross_validation.py
mglearn/plot_dbscan.py
mglearn/plot_decomposition.py
mglearn/plot_grid_search.py
mglearn/plot_helpers.py
mglearn/plot_improper_preprocessing.py
mglearn/plot_interactive_tree.py
mglearn/plot_kmeans.py
mglearn/plot_kneighbors_regularization.py
mglearn/plot_knn_classification.py
mglearn/plot_knn_regression.py
mglearn/plot_linear_regression.py
mglearn/plot_linear_svc_regularization.py
mglearn/plot_metrics.py
mglearn/plot_nmf.py
mglearn/plot_nn_graphs.py
mglearn/plot_pca.py
mglearn/plot_rbf_svm_parameters.py
mglearn/plot_ridge.py
mglearn/plot_scaling.py
mglearn/plot_tree_nonmonotonous.py
mglearn/plots.py
mglearn/tools.py
mglearn/data/adult.data
mglearn/data/citibike.csv
mglearn/data/ram_price.csv
mglearn-0.2.0.dist-info/METADATA
mglearn-0.2.0.dist-info/WHEEL
mglearn-0.2.0.dist-info/top_level.txt
mglearn-0.2.0.dist-info/RECORD
