Metadata-Version: 2.1
Name: mglearn
Version: 0.2.0
Summary: Helper functions for the book Introduction to machine learning with Python
Home-page: https://github.com/amueller/introduction_to_ml_with_python
Author: Andreas Mueller
Author-email: t3kcit@gmail.com
License: BSD
Keywords: machine learning ml sklearn scikit learn
